oodpexp/__init__.py
oodpexp-0.1.1.dist-info/LICENSE.txt
oodpexp-0.1.1.dist-info/METADATA
oodpexp-0.1.1.dist-info/WHEEL
oodpexp-0.1.1.dist-info/top_level.txt
oodpexp-0.1.1.dist-info/RECORD
