Metadata-Version: 2.1
Name: oodpexp
Version: 0.1.1
Summary: Helping students
Author: Charan
Author-email: charanreddy692007@gmail.com
Classifier: Programming Language :: Python :: 3
Classifier: License :: OSI Approved :: MIT License
Classifier: Operating System :: OS Independent
Requires-Python: >=3.6
License-File: LICENSE.txt
